pydevd_plugins/extensions/pydevd_plugin_syside.py
syside/__init__.py
syside/__main__.py
syside/_build_info.py
syside/_diagnostics.py
syside/_loading.py
syside/_platform.py
syside/core.abi3.so
syside/helpers.py
syside/py.typed
syside/cli/__init__.py
syside/cli/_logger.py
syside/cli/format.py
syside/core/__init__.pyi
syside/core/debug/__init__.pyi
syside/core/experimental/__init__.pyi
syside/core/experimental/viz/__init__.pyi
syside/core/experimental/viz/dot/__init__.pyi
syside/core/gc/__init__.pyi
syside/core/ide/__init__.pyi
syside/core/ide/lsp/__init__.pyi
syside/core/version/__init__.pyi
syside/debug/__init__.py
syside/experimental/__init__.py
syside/experimental/viz/__init__.py
syside/experimental/viz/dot/__init__.py
syside/gc/__init__.py
syside/ide/__init__.py
syside/ide/lsp/__init__.py
syside/json/__init__.py
syside/preview/__init__.py
syside/preview/_building.py
syside/preview/_loading.py
syside/sysml.library/LICENSE
syside/sysml.library/README.md
syside/sysml.library/Domain Libraries/Analysis/AnalysisTooling.sysml
syside/sysml.library/Domain Libraries/Analysis/SampledFunctions.sysml
syside/sysml.library/Domain Libraries/Analysis/StateSpaceRepresentation.sysml
syside/sysml.library/Domain Libraries/Analysis/TradeStudies.sysml
syside/sysml.library/Domain Libraries/Cause and Effect/CausationConnections.sysml
syside/sysml.library/Domain Libraries/Cause and Effect/CauseAndEffect.sysml
syside/sysml.library/Domain Libraries/Geometry/ShapeItems.sysml
syside/sysml.library/Domain Libraries/Geometry/SpatialItems.sysml
syside/sysml.library/Domain Libraries/Metadata/ImageMetadata.sysml
syside/sysml.library/Domain Libraries/Metadata/ModelingMetadata.sysml
syside/sysml.library/Domain Libraries/Metadata/ParametersOfInterestMetadata.sysml
syside/sysml.library/Domain Libraries/Metadata/RiskMetadata.sysml
syside/sysml.library/Domain Libraries/Quantities and Units/ISQ.sysml
syside/sysml.library/Domain Libraries/Quantities and Units/ISQAcoustics.sysml
syside-0.8.4.dist-info/licenses/LICENSE.txt
syside-0.8.4.dist-info/licenses/third-party-licenses.rst
syside-0.8.4.dist-info/METADATA
syside-0.8.4.dist-info/WHEEL
syside-0.8.4.dist-info/top_level.txt
syside-0.8.4.dist-info/RECORD
