Metadata-Version: 2.4
Name: syside
Version: 0.8.4
Summary: Syside Automator Python library for SysML v2 and KerML modeling languages.
Author-email: Sensmetry <syside@sensmetry.com>
License-Expression: LicenseRef-Proprietary
Project-URL: Homepage, https://sensmetry.com/syside
Project-URL: Issues, https://forum.sensmetry.com/c/syside/bug-reports/5
Project-URL: Documentation, https://docs.sensmetry.com
Project-URL: Community, https://forum.sensmetry.com
Project-URL: Changelog, https://forum.sensmetry.com/c/syside/changelogs/23
Keywords: syside,sysml,sysmlv2,sysml v2,kerml,mbse,systems engineering,model based systems engineering,automation
Classifier: Programming Language :: Python :: 3
Classifier: Programming Language :: Python :: 3.12
Classifier: Programming Language :: Python :: 3.13
Classifier: Intended Audience :: Developers
Classifier: Topic :: Scientific/Engineering
Classifier: Topic :: Software Development
Classifier: Typing :: Typed
Requires-Python: >=3.12
License-File: LICENSE.txt
License-File: third-party-licenses.rst
Requires-Dist: click>=8.1.7
Provides-Extra: ipython
Requires-Dist: ipython>=8.28.0; extra == "ipython"
Dynamic: license-file
